ocpa/__init__.py
ocpa/algo/__init__.py
ocpa/algo/conformance/__init__.py
ocpa/algo/conformance/alignments/__init__.py
ocpa/algo/conformance/alignments/algorithm.py
ocpa/algo/conformance/alignments/alignment.py
ocpa/algo/conformance/alignments/helperfunctions.py
ocpa/algo/conformance/constraint_monitoring/__init__.py
ocpa/algo/conformance/constraint_monitoring/algorithm.py
ocpa/algo/conformance/constraint_monitoring/versions/__init__.py
ocpa/algo/conformance/constraint_monitoring/versions/extensive_log_based.py
ocpa/algo/conformance/constraint_monitoring/versions/log_based.py
ocpa/algo/conformance/precision_and_fitness/__init__.py
ocpa/algo/conformance/precision_and_fitness/evaluator.py
ocpa/algo/conformance/precision_and_fitness/utils.py
ocpa/algo/conformance/precision_and_fitness/variants/__init__.py
ocpa/algo/conformance/precision_and_fitness/variants/replay_context.py
ocpa/algo/conformance/token_based_replay/__init__.py
ocpa/algo/conformance/token_based_replay/algorithm.py
ocpa/algo/conformance/token_based_replay/utils.py
ocpa/algo/conformance/token_based_replay/backward_replay/algorithm.py
ocpa/algo/conformance/token_based_replay/backward_replay/variants/backward_searching_tree.py
ocpa/algo/conformance/token_based_replay/backward_replay/variants/shortest_path.py
ocpa/algo/conformance/token_based_replay/enhancement/activity_caching.py
ocpa/algo/conformance/token_based_replay/enhancement/address_token_flooding.py
ocpa/algo/conformance/token_based_replay/variants/__init__.py
ocpa/algo/conformance/token_based_replay/variants/flattened_replay.py
ocpa/algo/conformance/token_based_replay/variants/object_centric_replay.py
ocpa/algo/discovery/__init__.py
ocpa/algo/discovery/enhanced_ocpn/__init__.py
ocpa/algo/discovery/enhanced_ocpn/algorithm.py
ocpa/algo/discovery/ocpn/__init__.py
ocpa/algo/discovery/ocpn/algorithm.py
ocpa/algo/discovery/ocpn/versions/__init__.py
ocpa/algo/discovery/ocpn/versions/inductive.py
ocpa/algo/discovery/ocpn/versions/new_inductive.py
ocpa-1.3.4.dist-info/LICENSE.txt
ocpa-1.3.4.dist-info/METADATA
ocpa-1.3.4.dist-info/WHEEL
ocpa-1.3.4.dist-info/top_level.txt
ocpa-1.3.4.dist-info/RECORD
