Metadata-Version: 2.1
Name: ocpa
Version: 1.3.4
Summary: Object-Centric Process Analysis (OCPA)
Home-page: https://github.com/ocpm/ocpa
Author: Jan Niklas Adams and Gyunam Park
Author-email: gnpark@pads.rwth-aachen.de
License: MIT
License-File: LICENSE.txt
